deephaven_server/__init__.py
deephaven_server/cli.py
deephaven_server/py.typed
deephaven_server/server.py
deephaven_server/start_jvm.py
deephaven_server/jars/HdrHistogram-2.2.2.jar
deephaven_server/jars/RoaringBitmap-1.3.0.jar
deephaven_server/jars/accessors-smart-2.5.2.jar
deephaven_server/jars/aggdesigner-algorithm-6.1.jar
deephaven_server/jars/aircompressor-2.0.2.jar
deephaven_server/jars/animal-sniffer-annotations-1.24.jar
deephaven_server/jars/annotations-13.0.jar
deephaven_server/jars/annotations-2.29.52.jar
deephaven_server/jars/annotations-4.1.1.4.jar
deephaven_server/jars/apache-client-2.29.52.jar
deephaven_server/jars/apiguardian-api-1.1.2.jar
deephaven_server/jars/arns-2.29.52.jar
deephaven_server/jars/arrow-compression-18.3.0.jar
deephaven_server/jars/arrow-format-18.3.0.jar
deephaven_server/jars/arrow-memory-core-18.3.0.jar
deephaven_server/jars/arrow-memory-netty-18.3.0.jar
deephaven_server/jars/arrow-memory-netty-buffer-patch-18.3.0.jar
deephaven_server/jars/arrow-vector-18.3.0.jar
deephaven_server/jars/asm-9.9.jar
deephaven_server/jars/asm-commons-9.9.jar
deephaven_server/jars/asm-tree-9.9.jar
deephaven_server/jars/auth-2.29.52.jar
deephaven_server/jars/avatica-core-1.27.0.jar
deephaven_server/jars/avatica-metrics-1.27.0.jar
deephaven_server/jars/avro-1.12.1.jar
deephaven_server/jars/aws-core-2.29.52.jar
deephaven_server/jars/aws-crt-0.33.3.jar
deephaven_server/jars/aws-crt-client-2.29.52.jar
deephaven_server/jars/aws-json-protocol-2.29.52.jar
deephaven_server/jars/aws-query-protocol-2.29.52.jar
deephaven_server/jars/aws-xml-protocol-2.29.52.jar
deephaven_server/jars/ayza-10.0.2.jar
deephaven_server/jars/ayza-for-jetty-10.0.2.jar
deephaven_server/jars/ayza-for-netty-10.0.2.jar
deephaven_server/jars/barrage-format-1.0.0.jar
deephaven_server/jars/caffeine-2.9.3.jar
deephaven_server/jars/calcite-core-1.41.0.jar
deephaven_server/jars/calcite-linq4j-1.41.0.jar
deephaven_server/jars/checker-qual-3.19.0.jar
deephaven_server/jars/checksums-2.29.52.jar
deephaven_server-41.1.dist-info/METADATA
deephaven_server-41.1.dist-info/WHEEL
deephaven_server-41.1.dist-info/entry_points.txt
deephaven_server-41.1.dist-info/top_level.txt
deephaven_server-41.1.dist-info/RECORD
