Metadata-Version: 2.1
Name: deephaven-server
Version: 41.1
Summary: Deephaven Embedded Server Python Package
Home-page: https://deephaven.io/
Author: Deephaven Data Labs
Author-email: python@deephaven.io
License: Deephaven Community License
Keywords: Deephaven Development
Classifier: Development Status :: 4 - Beta
Classifier: Intended Audience :: Developers
Classifier: Intended Audience :: Science/Research
Classifier: License :: Other/Proprietary License
Classifier: Programming Language :: Python
Classifier: Programming Language :: Python :: 3
Classifier: Programming Language :: Python :: 3 :: Only
Classifier: Programming Language :: Python :: 3.9
Classifier: Programming Language :: Python :: 3.10
Classifier: Programming Language :: Python :: 3.11
Classifier: Programming Language :: Python :: 3.12
Classifier: Programming Language :: Python :: 3.13
Requires-Python: >=3.9
Requires-Dist: jpy>=1.1.0
Requires-Dist: java-utilities
Requires-Dist: deephaven-core[autocomplete]==41.1
Requires-Dist: click>=8.1.7
